{
  "posts": [
    {
      "id": 12,
      "title": "create1",
      "content": "create12",
      "createdAt": "2022-09-04",
      "contnet": null
    },
    {
      "title": "patch test",
      "content": "patch test",
      "createdAt": "2022-09-05",
      "id": 13
    },
    {
      "title": "create2",
      "content": "create2\ntest",
      "createdAt": "2022-09-04",
      "id": 14,
      "contnet": null
    },
    {
      "title": "create3",
      "content": "create3",
      "createdAt": "2022-09-04",
      "id": 15
    },
    {
      "title": "create4",
      "content": "create4",
      "createdAt": "2022-09-04",
      "id": 16
    },
    {
      "title": "create5",
      "content": "create5",
      "createdAt": "2022-09-04",
      "id": 17
    },
    {
      "title": "create6",
      "content": "create6",
      "createdAt": "2022-09-04",
      "id": 18
    },
    {
      "title": "create7",
      "content": "create7",
      "createdAt": "2022-09-04",
      "id": 19
    },
    {
      "title": "dayTest",
      "content": "dayTest",
      "createdAt": "2022-09-05",
      "id": 20,
      "contnet": null
    },
    {
      "title": "t2",
      "content": "t2",
      "createdAt": "2022-09-06",
      "id": 21
    },
    {
      "title": "수정 t",
      "content": "수정 t",
      "id": 22
    },
    {
      "title": "321312",
      "content": "321312",
      "id": 23
    },
    {
      "title": "4141",
      "content": "4141",
      "id": 24
    },
    {
      "title": "11414",
      "content": "df",
      "id": 25
    },
    {
      "title": "123123",
      "content": "123123",
      "createdAt": 1662483940550,
      "id": 26
    }
  ],
  "profile": {
    "name": "typicode"
  }
}